{"lastUpdated":"2025-12-30T11:54:19.410Z","day":1,"companyName":"Suditi","sheetName":"Suditi","sections":{"registered":[{"slNo":"","studentName":"Registered Candidates List","rollNo":"","discipline":"","campus":""},{"slNo":"","studentName":"Sl. No","rollNo":"Student Name","discipline":"Roll No","campus":"Discipline"},{"slNo":"","studentName":1,"rollNo":"FATHIMA RAIHAN","discipline":"MFM/23/188","campus":"Master of Fashion Management"},{"slNo":"","studentName":2,"rollNo":"GAURAV KUMAR","discipline":"MFM/23/225","campus":"Master of Fashion Management"},{"slNo":"","studentName":3,"rollNo":"SIA MARWAH","discipline":"MFM/23/466","campus":"Master of Fashion Management"},{"slNo":"","studentName":4,"rollNo":"YASHIKA POWALE","discipline":"MFM/23/241","campus":"Master of Fashion Management"},{"slNo":"","studentName":5,"rollNo":"SHRUTI KUMARI","discipline":"MFM/23/1143","campus":"Master of Fashion Management"},{"slNo":"","studentName":6,"rollNo":"SAI SWETA DASH","discipline":"MFM/23/275","campus":"Master of Fashion Management"},{"slNo":"","studentName":7,"rollNo":"DHRISYA A SUNIL","discipline":"MFM/23/1050","campus":"Master of Fashion Management"},{"slNo":"","studentName":8,"rollNo":"HARSHA.S","discipline":"MFM/23/985","campus":"Master of Fashion Management"},{"slNo":"","studentName":9,"rollNo":"ANJANA SIVADASAN NAIR","discipline":"MFM/23/84","campus":"Master of Fashion Management"},{"slNo":"","studentName":10,"rollNo":"ANJANA SIVADASAN NAIR","discipline":"MFM/23/84","campus":"Master of Fashion Management"},{"slNo":"","studentName":11,"rollNo":"S JAVITH","discipline":"MFM/23/454","campus":"Master of Fashion Management"},{"slNo":"","studentName":12,"rollNo":"S JAVITH","discipline":"MFM/23/454","campus":"Master of Fashion Management"},{"slNo":"","studentName":13,"rollNo":"ATUL A. BEHERA","discipline":"MFM/23/1077","campus":"Master of Fashion Management"},{"slNo":"","studentName":14,"rollNo":"ATUL A. BEHERA","discipline":"MFM/23/1077","campus":"Master of Fashion Management"},{"slNo":"","studentName":15,"rollNo":"AANCHAL GOLCHHA","discipline":"MFM/23/113","campus":"Master of Fashion Management"},{"slNo":"","studentName":16,"rollNo":"KRITIKA SINGH","discipline":"MFM/23/105","campus":"Master of Fashion Management"},{"slNo":"","studentName":17,"rollNo":"SHIVANGI DUBEY","discipline":"MFM/23/156","campus":"Master of Fashion Management"},{"slNo":"","studentName":18,"rollNo":"TANYA SACHAN","discipline":"MFM/23/583","campus":"Master of Fashion Management"},{"slNo":"","studentName":19,"rollNo":"TINA RATNOO","discipline":"MFM/23/457","campus":"Master of Fashion Management"},{"slNo":"","studentName":20,"rollNo":"ADITI SAINI","discipline":"MFM/23/449","campus":"Master of Fashion Management"},{"slNo":"","studentName":21,"rollNo":"PULKIT KUMAR","discipline":"MFM/23/684","campus":"Master of Fashion Management"},{"slNo":"","studentName":22,"rollNo":"V. VAISHNAVI","discipline":"MFM/23/140","campus":"Master of Fashion Management"},{"slNo":"","studentName":23,"rollNo":"STUTI JAISWAL","discipline":"MFM/23/469","campus":"Master of Fashion Management"},{"slNo":"","studentName":24,"rollNo":"KHUSHI HITESH MADIA","discipline":"MFM/23/110","campus":"Master of Fashion Management"},{"slNo":"","studentName":25,"rollNo":"JAHNVI CHAKRABORTY","discipline":"MFM/23/101","campus":"Master of Fashion Management"},{"slNo":"","studentName":26,"rollNo":"RITIK RAJAN","discipline":"MFM/23/372","campus":"Master of Fashion Management"},{"slNo":"","studentName":27,"rollNo":"YOSHITA JAISWAL","discipline":"MFM/23/552","campus":"Master of Fashion Management"},{"slNo":"","studentName":28,"rollNo":"YOSHITA JAISWAL","discipline":"MFM/23/552","campus":"Master of Fashion Management"},{"slNo":"","studentName":29,"rollNo":"B SWATHI","discipline":"MFM/23/1173","campus":"Master of Fashion Management"},{"slNo":"","studentName":30,"rollNo":"ARYAN DEWANGAN","discipline":"MFM/23/865","campus":"Master of Fashion Management"},{"slNo":"","studentName":31,"rollNo":"MD KASIF","discipline":"MFM/23/967","campus":"Master of Fashion Management"},{"slNo":"","studentName":32,"rollNo":"SHARAYU NAVNATH JADHAV","discipline":"MFM/23/739","campus":"Master of Fashion Management"},{"slNo":"","studentName":33,"rollNo":"TANISHA GUPTA","discipline":"MFM/23/1145","campus":"Master of Fashion Management"},{"slNo":"","studentName":34,"rollNo":"NISHIKA DAS","discipline":"MFM/23/674","campus":"Master of Fashion Management"},{"slNo":"","studentName":35,"rollNo":"VARUN SONI","discipline":"MFM/23/1051","campus":"Master of Fashion Management"},{"slNo":"","studentName":36,"rollNo":"SAMEERA FARIN A","discipline":"MD/23/617","campus":"Master of Design"},{"slNo":"","studentName":37,"rollNo":"PUSHPANJALI GIRI","discipline":"MFM/23/387","campus":"Master of Fashion Management"},{"slNo":"","studentName":38,"rollNo":"SHWETA GOPINATHAN","discipline":"MFM/23/538","campus":"Master of Fashion Management"},{"slNo":"","studentName":39,"rollNo":"SHWETA GOPINATHAN","discipline":"MFM/23/538","campus":"Master of Fashion Management"},{"slNo":"","studentName":40,"rollNo":"GOSARIPALLI SALMA","discipline":"MFM/23/626","campus":"Master of Fashion Management"},{"slNo":"","studentName":41,"rollNo":"P PRASHITHA","discipline":"MFM/23/669","campus":"Master of Fashion Management"},{"slNo":"","studentName":42,"rollNo":"NIVEA MARTIN","discipline":"MFM/23/695","campus":"Master of Fashion Management"},{"slNo":"","studentName":43,"rollNo":"SUCHISMITA GUHA","discipline":"MFM/23/179","campus":"Master of Fashion Management"},{"slNo":"","studentName":44,"rollNo":"LAKHSHITA UPADHYAY","discipline":"MFM/23/219","campus":"Master of Fashion Management"},{"slNo":"","studentName":45,"rollNo":"SPURTHI H K","discipline":"MFM/23/207","campus":"Master of Fashion Management"},{"slNo":"","studentName":46,"rollNo":"SPURTHI H K","discipline":"MFM/23/207","campus":"Master of Fashion Management"},{"slNo":"","studentName":47,"rollNo":"DAMINI PACHAURI","discipline":"MFM/23/565","campus":"Master of Fashion Management"},{"slNo":"","studentName":48,"rollNo":"DAMINI PACHAURI","discipline":"MFM/23/565","campus":"Master of Fashion Management"},{"slNo":"","studentName":49,"rollNo":"PRANAB KANTI SINHA","discipline":"MFM/23/989","campus":"Master of Fashion Management"},{"slNo":"","studentName":50,"rollNo":"PRANAB KANTI SINHA","discipline":"MFM/23/989","campus":"Master of Fashion Management"},{"slNo":"","studentName":51,"rollNo":"YUKTAKHI GOGOI","discipline":"MFM/23/476","campus":"Master of Fashion Management"},{"slNo":"","studentName":52,"rollNo":"ASIN BAKLIWAL JAIN","discipline":"MD/23/298","campus":"Master of Design"},{"slNo":"","studentName":53,"rollNo":"IDITRI MAHAJAN","discipline":"MFM/23/52","campus":"Master of Fashion Management"},{"slNo":"","studentName":54,"rollNo":"SHREYA YADAV","discipline":"MFM/23/280","campus":"Master of Fashion Management"},{"slNo":"","studentName":55,"rollNo":"SHREYA YADAV","discipline":"MFM/23/280","campus":"Master of Fashion Management"},{"slNo":"","studentName":56,"rollNo":"RAVAL PRIYA JIGNESH","discipline":"MFM/23/209","campus":"Master of Fashion Management"},{"slNo":"","studentName":57,"rollNo":"HARSH SHARMA","discipline":"MFT/23/35","campus":"Master of Fashion Technology"},{"slNo":"","studentName":58,"rollNo":"HARSH SHARMA","discipline":"MFT/23/35","campus":"Master of Fashion Technology"},{"slNo":"","studentName":59,"rollNo":"VIKASH KUMAR","discipline":"MFM/23/635","campus":"Master of Fashion Management"},{"slNo":"","studentName":60,"rollNo":"NILANGI VASANT TALMALE","discipline":"MFM/23/852","campus":"Master of Fashion Management"},{"slNo":"","studentName":61,"rollNo":"RAHUL RAJ","discipline":"MFM/23/909","campus":"Master of Fashion Management"},{"slNo":"","studentName":62,"rollNo":"KASTURI BUDHIA","discipline":"MFM/23/571","campus":"Master of Fashion Management"},{"slNo":"","studentName":63,"rollNo":"SHRITI MANDAL","discipline":"MFM/23/878","campus":"Master of Fashion Management"},{"slNo":"","studentName":64,"rollNo":"SONALI DUTTA","discipline":"MFM/23/870","campus":"Master of Fashion Management"},{"slNo":"","studentName":65,"rollNo":"SAISHRUTI  VISHAL  KROVVIDI","discipline":"MFM/23/547","campus":"Master of Fashion Management"},{"slNo":"","studentName":66,"rollNo":"SABBINENI VAMSI KRISHNA","discipline":"MFM/23/542","campus":"Master of Fashion Management"},{"slNo":"","studentName":67,"rollNo":"SABBINENI VAMSI KRISHNA","discipline":"MFM/23/542","campus":"Master of Fashion Management"},{"slNo":"","studentName":68,"rollNo":"VAISHNAVI BABASAHEB CHAME","discipline":"MFM/23/961","campus":"Master of Fashion Management"},{"slNo":"","studentName":69,"rollNo":"SANJANA SHAW","discipline":"MFM/23/997","campus":"Master of Fashion Management"},{"slNo":"","studentName":70,"rollNo":"KHAVIN DHIR","discipline":"MFM/23/888","campus":"Master of Fashion Management"},{"slNo":"","studentName":71,"rollNo":"KHAVIN DHIR","discipline":"MFM/23/888","campus":"Master of Fashion Management"},{"slNo":"","studentName":72,"rollNo":"SANA MAHVISH","discipline":"MFM/23/854","campus":"Master of Fashion Management"},{"slNo":"","studentName":73,"rollNo":"KARTHIK S","discipline":"MFM/23/782","campus":"Master of Fashion Management"}],"round1":[{"slNo":"","studentName":"First Round Shortlisted Candidates List","rollNo":"","discipline":"","campus":""},{"slNo":"","studentName":"Sl. No","rollNo":"Student Name","discipline":"Roll No","campus":"Discipline"},{"slNo":"","studentName":1,"rollNo":"KRITIKA SINGH","discipline":"MFM/23/105","campus":"Master of Fashion Management"},{"slNo":"","studentName":2,"rollNo":"PRANAB KANTI SINHA","discipline":"MFM/23/989","campus":"Master of Fashion Management"},{"slNo":"","studentName":3,"rollNo":"LAKHSHITA UPADHYAY","discipline":"MFM/23/219","campus":"Master of Fashion Management"},{"slNo":"","studentName":4,"rollNo":"SAISHRUTI  VISHAL  KROVVIDI","discipline":"MFM/23/547","campus":"Master of Fashion Management"},{"slNo":"","studentName":5,"rollNo":"SHWETA GOPINATHAN","discipline":"MFM/23/538","campus":"Master of Fashion Management"},{"slNo":"","studentName":6,"rollNo":"DAMINI PACHAURI","discipline":"MFM/23/565","campus":"Master of Fashion Management"},{"slNo":"","studentName":7,"rollNo":"PUSHPANJALI GIRI","discipline":"MFM/23/387","campus":"Master of Fashion Management"},{"slNo":"","studentName":8,"rollNo":"","discipline":"","campus":""},{"slNo":"","studentName":9,"rollNo":"","discipline":"","campus":""},{"slNo":"","studentName":10,"rollNo":"","discipline":"","campus":""},{"slNo":"","studentName":11,"rollNo":"","discipline":"","campus":""},{"slNo":"","studentName":12,"rollNo":"","discipline":"","campus":""},{"slNo":"","studentName":13,"rollNo":"","discipline":"","campus":""},{"slNo":"","studentName":14,"rollNo":"","discipline":"","campus":""},{"slNo":"","studentName":15,"rollNo":"","discipline":"","campus":""},{"slNo":"","studentName":16,"rollNo":"","discipline":"","campus":""},{"slNo":"","studentName":17,"rollNo":"","discipline":"","campus":""},{"slNo":"","studentName":18,"rollNo":"","discipline":"","campus":""},{"slNo":"","studentName":19,"rollNo":"","discipline":"","campus":""},{"slNo":"","studentName":20,"rollNo":"","discipline":"","campus":""},{"slNo":"","studentName":21,"rollNo":"","discipline":"","campus":""},{"slNo":"","studentName":22,"rollNo":"","discipline":"","campus":""},{"slNo":"","studentName":23,"rollNo":"","discipline":"","campus":""},{"slNo":"","studentName":24,"rollNo":"","discipline":"","campus":""},{"slNo":"","studentName":25,"rollNo":"","discipline":"","campus":""},{"slNo":"","studentName":26,"rollNo":"","discipline":"","campus":""}],"round2":[{"slNo":"","studentName":"Final List of Selected Candidates","rollNo":"","discipline":"","campus":""},{"slNo":"","studentName":"Sl. No","rollNo":"Student Name","discipline":"Roll No","campus":"Discipline"},{"slNo":"","studentName":1,"rollNo":"SHWETA GOPINATHAN","discipline":"MFM/23/538","campus":"Master of Fashion Management"},{"slNo":"","studentName":2,"rollNo":"DAMINI PACHAURI","discipline":"MFM/23/565","campus":"Master of Fashion Management"},{"slNo":"","studentName":3,"rollNo":"PUSHPANJALI GIRI","discipline":"MFM/23/387","campus":"Master of Fashion Management"},{"slNo":"","studentName":4,"rollNo":"","discipline":"","campus":""}]}}